demo/app.py
deepseek_code-0.1.0.dist-info/METADATA
deepseek_code-0.1.0.dist-info/WHEEL
deepseek_code-0.1.0.dist-info/top_level.txt
deepseek_code-0.1.0.dist-info/RECORD
